README.rst
pure_func.py
setup.py
pure_func.egg-info/PKG-INFO
pure_func.egg-info/SOURCES.txt
pure_func.egg-info/dependency_links.txt
pure_func.egg-info/top_level.txt