Metadata-Version: 1.1
Name: pure-func
Version: 1.2
Summary: Pure-func helps to write pure functions in python
Home-page: http://github.com/adfinis-sygroup/pure_func
Author: Adfinis SyGroup AG
Author-email: ganwell@fangorn.ch
License: UNKNOWN
Keywords: pure functional programming unit-testing
Platform: UNKNOWN
Classifier: Development Status :: 5 - Production/Stable
Classifier: Intended Audience :: Developers
Classifier: Intended Audience :: Information Technology
Classifier: License :: OSI Approved :: MIT License
Classifier: Natural Language :: English
Classifier: Operating System :: OS Independent
Classifier: Programming Language :: Python :: 3.4
Classifier: Programming Language :: Python :: 3.5
Classifier: Programming Language :: Python :: 3.6
Classifier: Topic :: Software Development :: Testing
Classifier: Topic :: Software Development :: Libraries
